drugtargetcom/__init__.py
drugtargetcom/main.py
DrugTargetCom-0.1.2.dist-info/METADATA
DrugTargetCom-0.1.2.dist-info/WHEEL
DrugTargetCom-0.1.2.dist-info/entry_points.txt
DrugTargetCom-0.1.2.dist-info/top_level.txt
DrugTargetCom-0.1.2.dist-info/RECORD
