Metadata-Version: 2.1
Name: DrugTargetCom
Version: 0.1.2
Summary: Genetic Algorithm Based Combination Therapy Finder
Author: Seyedeh Sadaf Asfa & Reza Arshinchi Bonab
Classifier: Programming Language :: Python :: 3
Classifier: License :: OSI Approved :: MIT License
Classifier: Operating System :: OS Independent
Requires-Python: >=3.6
Requires-Dist: pandas
Requires-Dist: openpyxl
Requires-Dist: deap
Requires-Dist: numpy
